pytest_recap/__init__.py
pytest_recap/cloud.py
pytest_recap/models.py
pytest_recap/plugin.py
pytest_recap/pytest-recap.code-workspace
pytest_recap/storage.py
pytest_recap-0.9.2.dist-info/METADATA
pytest_recap-0.9.2.dist-info/WHEEL
pytest_recap-0.9.2.dist-info/entry_points.txt
pytest_recap-0.9.2.dist-info/RECORD
