Metadata-Version: 2.4
Name: pytest-recap
Version: 0.9.2
Summary: Capture your test sessions. Recap the results.
Author-email: Jeff Wright <jeff.washcloth@gmail.com>
Requires-Python: >=3.9
Requires-Dist: filelock>=3.0
Requires-Dist: jinja2>=2.11
Requires-Dist: pytest-cov>=2.10
Requires-Dist: pytest-rerunfailures>=10.0
Requires-Dist: pytest>=6.2.0
Requires-Dist: requests>=2.20
Requires-Dist: typer>=0.16.0
